custom_sklearn/__init__.py
custom_sklearn/module.py
custom_sklearn-0.4.3.dist-info/LICENSE
custom_sklearn-0.4.3.dist-info/METADATA
custom_sklearn-0.4.3.dist-info/WHEEL
custom_sklearn-0.4.3.dist-info/top_level.txt
custom_sklearn-0.4.3.dist-info/RECORD
