Metadata-Version: 2.2
Name: custom_sklearn
Version: 0.4.3
Summary: A simple example package
Author: WeareUs
Author-email: WeareUs <1customer11service1@gmail.com>
License: MIT License
Requires-Python: >=3.6
License-File: LICENSE
Dynamic: author
Dynamic: requires-python
